tjsp/__init__.py
tjsp/paths.py
tjsp/tjsp_dates.py
tjsp/tjsp_update.py
tjsp/update.py
tjsp/data/date.txt
tjsp/data/tabela_debitos_judiciais.csv
tjsp/data/tabela_debitos_judiciais.pdf
tjsp-0.0.7.dist-info/LICENSE
tjsp-0.0.7.dist-info/METADATA
tjsp-0.0.7.dist-info/WHEEL
tjsp-0.0.7.dist-info/top_level.txt
tjsp-0.0.7.dist-info/RECORD
