Metadata-Version: 2.1
Name: tjsp
Version: 0.0.7
Summary: Série Temporal das Taxas do Tribunal de Justiça do Estado de São Paulo e métodos para recuperar informações das taxas
Home-page: https://github.com/gaemapiracicaba/sp_tjsp_correcao_monetaria
Author: Michel Metran
Author-email: michelmetran@gmail.com
Keywords: python,tjsp,finance
Classifier: Programming Language :: Python :: 3
Classifier: License :: OSI Approved :: MIT License
Classifier: Operating System :: OS Independent
Classifier: Natural Language :: Portuguese
Classifier: Intended Audience :: Developers
Requires-Python: >=3
License-File: LICENSE
Requires-Dist: requests (>=2.25.1)
Requires-Dist: tabula-py (>=2.2.0)
Requires-Dist: pandas (>=1.1.0)
